[
  {
    "slug": "sunlight-mountain",
    "typical_season_start": "Mid December",
    "typical_season_end": "Early April",
    "nearest_airport_code": "GWS",
    "nearest_airport_name": "Glenwood Springs Municipal Airport",
    "annual_snowfall_inches": 250,
    "terrain_park_count": 1,
    "has_terrain_park": true,
    "has_glades": null,
    "has_tubing": null,
    "has_night_skiing": false,
    "has_lodging": null,
    "vertical_drop_ft": 2010,
    "total_acres": 680,
    "total_lifts": 3,
    "longest_run_miles": 2.5,
    "source_url": "https://en.wikipedia.org/wiki/Sunlight_Ski_Area",
    "exact_quote": "2,010 feet (610 m) ... 680 acres (2.8 km2) ... 67 total ... 3 chairlifts - (1 triple, 2 double) ... 2.5 miles (4.0 km) ... 250 in (635 cm) ... Night skiing: None ... Glenwood Springs, Colorado: 12 miles (20 km)",
    "notes": "Sunlight Mountain Resort, Glenwood Springs CO. Wikipedia: 2010ft vert, 680ac, 67 trails (20/55/20/5), 3 chairs (triple+2 doubles), 2.5mi longest, 250\" snow, no night skiing. Season Dec 13 2025-Apr 5 2026 per visitglenwood.com. No slopeside lodging-only Glenwood Springs town shuttle. GWS small/no commercial; EGE Eagle County 90mi closest commercial."
  },
  {
    "slug": "sunrise-park-resort",
    "typical_season_start": "Thanksgiving",
    "typical_season_end": "Late March",
    "nearest_airport_code": "SOW",
    "nearest_airport_name": "Show Low Regional Airport",
    "annual_snowfall_inches": 250,
    "terrain_park_count": 1,
    "has_terrain_park": true,
    "has_glades": null,
    "has_tubing": true,
    "has_night_skiing": true,
    "has_lodging": true,
    "vertical_drop_ft": 1900,
    "total_acres": 1200,
    "total_lifts": 8,
    "longest_run_miles": 2.75,
    "source_url": "https://en.wikipedia.org/wiki/Sunrise_Park_Resort",
    "exact_quote": "1,900 ft (580 m) ... 1,200 acres (4.9 km2) ... 67 total ... 8 Operational Chairlifts ... 2.75 miles (4.43 km) 'Lonestar' on Cyclone Circle ... 250 in/year (6.35 m/year) ... 1 ... a snow tubing hill ... Yes (4:30 p.m. - 8:00 p.m. on limited days) ... from Thanksgiving through the end of March",
    "notes": "Sunrise Park Resort, White Mountain Apache Tribe AZ. Wikipedia: 1900ft vert, 1200ac, 67 trails, 8 chairs, 2.75mi longest, 250\" snow, 1 park, tubing, night ski limited days, season Thanksgiving-end Mar. Sunrise Park Lodge on-site. SOW Show Low ~25mi closest commercial."
  },
  {
    "slug": "swain-resort",
    "typical_season_start": null,
    "typical_season_end": null,
    "nearest_airport_code": "ROC",
    "nearest_airport_name": "Greater Rochester International Airport",
    "annual_snowfall_inches": 130,
    "terrain_park_count": null,
    "has_terrain_park": null,
    "has_glades": null,
    "has_tubing": null,
    "has_night_skiing": null,
    "has_lodging": null,
    "vertical_drop_ft": 650,
    "total_acres": 120,
    "total_lifts": 5,
    "longest_run_miles": 1.0,
    "source_url": "https://nyskiblog.com/directory/ny-ski-areas/western-ny/swain/",
    "exact_quote": "vertical drop of 650 feet ... 120 acres of skiable terrain on 35 trails ... 3 quad chairs, 1 double chair, and 1 surface lift, for a total of 5 lifts ... longest run being 5,280 feet ... annual snowfall of 130 inches",
    "notes": "Swain Resort, Swain NY (western NY/Finger Lakes region). NYSkiBlog/OnTheSnow: 650ft vert, 120ac, 35 trails, 5 lifts (3 quads+1 double+1 surface), 1mi=5280ft longest, 130\" snow. ROC Rochester ~60mi N closest commercial; ELM Elmira closer but smaller."
  },
  {
    "slug": "swiss-valley",
    "typical_season_start": null,
    "typical_season_end": null,
    "nearest_airport_code": "SBN",
    "nearest_airport_name": "South Bend International Airport",
    "annual_snowfall_inches": 60,
    "terrain_park_count": null,
    "has_terrain_park": null,
    "has_glades": null,
    "has_tubing": null,
    "has_night_skiing": null,
    "has_lodging": false,
    "vertical_drop_ft": 225,
    "total_acres": 60,
    "total_lifts": 7,
    "longest_run_miles": null,
    "source_url": "https://www.onthesnow.com/michigan/swiss-valley/ski-resort",
    "exact_quote": "Vertical Drop: 225 feet ... 60 acres of terrain over 11 trails ... 7 lifts of 3 types ... two quad chairlifts, one triple chairlift and four rope tows in the learning area ... 60 inches of snowfall on average each year",
    "notes": "Swiss Valley Ski & Snowboard Area, Jones MI. OnTheSnow: 225ft vert, 60ac, 11 trails (some sources 10-12), 7 lifts (2 quads+1 triple+4 rope tows), 60\" snow. Day-use only, no lodging. SBN South Bend IN ~35mi SW closest commercial."
  },
  {
    "slug": "tahoe-donner-downhill",
    "typical_season_start": null,
    "typical_season_end": null,
    "nearest_airport_code": "RNO",
    "nearest_airport_name": "Reno-Tahoe International Airport",
    "annual_snowfall_inches": null,
    "terrain_park_count": null,
    "has_terrain_park": null,
    "has_glades": null,
    "has_tubing": null,
    "has_night_skiing": false,
    "has_lodging": null,
    "vertical_drop_ft": 600,
    "total_acres": 120,
    "total_lifts": 5,
    "longest_run_miles": null,
    "source_url": "https://en.wikipedia.org/wiki/Tahoe_Donner_Downhill_Ski_Area",
    "exact_quote": "600 ft (180 m) ... 120 acres (49 ha) ... 14 total ... 5 lifts: (1 quad, 1 triple, 3 conveyors) ... Mile Run ... Night skiing: None",
    "notes": "Tahoe Donner Downhill Ski Area, Truckee CA. Wikipedia: 600ft vert, 120ac, 14 trails (30/40/30), 5 lifts (quad+triple+3 conveyors), 'Mile Run' longest, no night ski. Snowfall not specified on WP. RNO Reno ~35mi E closest commercial."
  },
  {
    "slug": "tamarack",
    "typical_season_start": null,
    "typical_season_end": null,
    "nearest_airport_code": "BOI",
    "nearest_airport_name": "Boise Airport",
    "annual_snowfall_inches": 300,
    "terrain_park_count": 3,
    "has_terrain_park": true,
    "has_glades": null,
    "has_tubing": null,
    "has_night_skiing": false,
    "has_lodging": true,
    "vertical_drop_ft": 2760,
    "total_acres": 1100,
    "total_lifts": 7,
    "longest_run_miles": null,
    "source_url": "https://en.wikipedia.org/wiki/Tamarack_Resort",
    "exact_quote": "2,760 ft (841 m) ... 1,100 acres (4.5 km2) ... 50 ... 7 chairlifts ... 3 hi-speed quad, 2 fixed quad, 2 surface ... 300 in (760 cm) ... 3 ... None ... The Village contains 56 Phase I residences",
    "notes": "Tamarack Resort, Donnelly ID. Wikipedia: 2760ft vert, 1100ac, 50 trails (17/45/38), 7 chairs, 300\" snow, 3 parks, no night, 56-unit village lodging. BOI Boise ~100mi S closest commercial."
  },
  {
    "slug": "taos-ski-valley",
    "typical_season_start": null,
    "typical_season_end": null,
    "nearest_airport_code": "ABQ",
    "nearest_airport_name": "Albuquerque International Sunport",
    "annual_snowfall_inches": 300,
    "terrain_park_count": 2,
    "has_terrain_park": true,
    "has_glades": null,
    "has_tubing": null,
    "has_night_skiing": false,
    "has_lodging": true,
    "vertical_drop_ft": 3281,
    "total_acres": 1294,
    "total_lifts": 14,
    "longest_run_miles": 5.0,
    "source_url": "https://en.wikipedia.org/wiki/Taos_Ski_Valley",
    "exact_quote": "3,281 ft (1,000 m) ... 1,294 acres (5.2 km2) ... 110 ... 14 lifts: 1 gondola lift, 4 quads, 4 triples, 1 double, 4 surface lifts ... 5 mi (8 km) ... 300 in (760 cm) ... 2 ... No ... hotels, private home rentals, condominiums and alpine styled bed and breakfasts",
    "notes": "Taos Ski Valley NM. Wikipedia: 3281ft vert, 1294ac, 110 trails (24/25/51), 14 lifts incl gondola, 5mi longest, 300\" snow, 2 parks, no night, village lodging. ABQ Albuquerque ~152mi closest major; TSM Taos Regional small."
  },
  {
    "slug": "telluride",
    "typical_season_start": null,
    "typical_season_end": null,
    "nearest_airport_code": "TEX",
    "nearest_airport_name": "Telluride Regional Airport",
    "annual_snowfall_inches": 330,
    "terrain_park_count": 3,
    "has_terrain_park": true,
    "has_glades": null,
    "has_tubing": null,
    "has_night_skiing": false,
    "has_lodging": true,
    "vertical_drop_ft": 3845,
    "total_acres": 2000,
    "total_lifts": 18,
    "longest_run_miles": 4.6,
    "source_url": "https://en.wikipedia.org/wiki/Telluride_Ski_Resort",
    "exact_quote": "4,425 ft (1,349 m) including hike-to ... 3,845 ft (1,172 m) lift-served ... 2,000 acres (8.1 km2) ... 127 ... 2 gondolas, 12 chairlifts (7 high-speed quads, 1 quad, 2 triples, 2 doubles), 2 surface lifts, and 2 magic carpets ... Galloping Goose ... 4.6 miles (7.4 km) ... 330 in/year (838 cm/year) ... 3 ... none",
    "notes": "Telluride Ski Resort CO. Wikipedia: 3845ft lift-served vert (4425 w/hike), 2000ac, 127 trails (23/36/41), 18 lifts total (2 gondolas+12 chairs+2 surface+2 carpets), Galloping Goose 4.6mi longest, 330\" snow, 3 parks, no night. Owns Inn at Lost Creek + Peaks Resort. TEX Telluride local; MTJ Montrose ~65mi for bigger jets."
  },
  {
    "slug": "tenney-mountain",
    "typical_season_start": null,
    "typical_season_end": null,
    "nearest_airport_code": "MHT",
    "nearest_airport_name": "Manchester-Boston Regional Airport",
    "annual_snowfall_inches": null,
    "terrain_park_count": null,
    "has_terrain_park": true,
    "has_glades": null,
    "has_tubing": true,
    "has_night_skiing": null,
    "has_lodging": null,
    "vertical_drop_ft": 1400,
    "total_acres": 110,
    "total_lifts": 3,
    "longest_run_miles": null,
    "source_url": "https://en.wikipedia.org/wiki/Tenney_Mountain_Ski_Resort",
    "exact_quote": "vertical drop of 1,400 feet (430 m) ... 110 acres (45 ha) ... 45 trails ... three lifts: a triple chair, a double chair and a Pomalift ... Terrain Parks: Yes ... tubing ... since February 2017 ... 85% of terrain",
    "notes": "Tenney Mountain Ski Resort, Plymouth NH. Wikipedia: 1400ft vert, 110ac, 45 trails (OnTheSnow lists 53), 3 lifts (triple+double+pomalift), terrain park yes, tubing since 2017, snowmaking 85%. Snowfall ~44\" per OnTheSnow but not in WP. MHT Manchester ~70mi S closest commercial."
  },
  {
    "slug": "terry-peak",
    "typical_season_start": null,
    "typical_season_end": null,
    "nearest_airport_code": "RAP",
    "nearest_airport_name": "Rapid City Regional Airport",
    "annual_snowfall_inches": null,
    "terrain_park_count": 1,
    "has_terrain_park": true,
    "has_glades": null,
    "has_tubing": null,
    "has_night_skiing": null,
    "has_lodging": null,
    "vertical_drop_ft": 1164,
    "total_acres": 450,
    "total_lifts": 5,
    "longest_run_miles": null,
    "source_url": "https://en.wikipedia.org/wiki/Terry_Peak",
    "exact_quote": "1,164 feet (355 m) ... 450 acres (1.8 km2) ... 30 total ... 4 chairlifts ... 1 magic carpet ... 1 ... Rapid City ... 50 miles (80 km)",
    "notes": "Terry Peak Ski Area, Lead SD (Black Hills). Wikipedia: 1164ft vert, 450ac, 30 trails, 5 lifts (4 chairs+1 carpet), 1 park. Snowfall not in WP. RAP Rapid City ~50mi E closest commercial."
  },
  {
    "slug": "teton-pass",
    "typical_season_start": null,
    "typical_season_end": null,
    "nearest_airport_code": "GTF",
    "nearest_airport_name": "Great Falls International Airport",
    "annual_snowfall_inches": 300,
    "terrain_park_count": null,
    "has_terrain_park": null,
    "has_glades": null,
    "has_tubing": null,
    "has_night_skiing": null,
    "has_lodging": null,
    "vertical_drop_ft": 1000,
    "total_acres": 400,
    "total_lifts": 3,
    "longest_run_miles": null,
    "source_url": "https://www.skitetonmt.com/mountain-info/trail-map-statistics",
    "exact_quote": "1,000 feet of vertical drop and access to additional hike-to backcountry terrain rising another 1,300 feet ... 400 skiable acres with 43 downhill runs ... one fixed-grip double chairlift that accesses the primary terrain on Mount Lockhart and two surface lifts (a rope tow and a magic carpet) ... average of 300 inches of annual snowfall",
    "notes": "Teton Pass Ski Area, Choteau MT (Lewis & Clark NF). Resort site: 1000ft lift vert (+1300 hike), 400ac, 43 runs, 3 lifts (1 double chair+rope+carpet), 300\" snow. ~30mi west of Choteau. GTF Great Falls ~80mi closest commercial."
  },
  {
    "slug": "the-highlands",
    "typical_season_start": null,
    "typical_season_end": null,
    "nearest_airport_code": "PLN",
    "nearest_airport_name": "Pellston Regional Airport",
    "annual_snowfall_inches": null,
    "terrain_park_count": 3,
    "has_terrain_park": true,
    "has_glades": null,
    "has_tubing": null,
    "has_night_skiing": null,
    "has_lodging": true,
    "vertical_drop_ft": 500,
    "total_acres": 300,
    "total_lifts": null,
    "longest_run_miles": null,
    "source_url": "https://en.wikipedia.org/wiki/Boyne_Highlands",
    "exact_quote": "500 feet (150 m) ... 300 acres (1.2 km2) ... 55 ... Terrain Parks: Yes, 3 ... Snowmaking: Yes, 93%",
    "notes": "The Highlands (formerly Boyne Highlands), Harbor Springs MI. Wikipedia: 500ft vert, 300ac, 55 trails, 3 parks, 93% snowmaking. Lift count not given explicitly. Boyne-owned with on-site Highlands Inn lodging. PLN Pellston ~12mi N closest commercial."
  },
  {
    "slug": "the-omni-homestead-resort",
    "typical_season_start": null,
    "typical_season_end": null,
    "nearest_airport_code": "ROA",
    "nearest_airport_name": "Roanoke-Blacksburg Regional Airport",
    "annual_snowfall_inches": null,
    "terrain_park_count": null,
    "has_terrain_park": null,
    "has_glades": null,
    "has_tubing": true,
    "has_night_skiing": null,
    "has_lodging": true,
    "vertical_drop_ft": 700,
    "total_acres": 42,
    "total_lifts": 3,
    "longest_run_miles": null,
    "source_url": "https://www.onthesnow.com/virginia/the-homestead-ski-area/ski-resort",
    "exact_quote": "10 trails across 42 acres of skiable terrain, with a vertical drop of 700 feet ... three lifts, including a double chairlift and two surface lifts ... Penguin Slides Tubing Park ... tube runs are 900 feet long with a 120-foot drop ... snowtubing and ice skating",
    "notes": "Omni Homestead Resort, Hot Springs VA. OnTheSnow/Omni site: 700ft vert, 42ac, 10 trails (10/30/50), 3 lifts (1 double+2 surface), tubing (Penguin Slides), founded 1959 oldest VA ski. Full hotel lodging. ROA Roanoke ~75mi S closest commercial."
  },
  {
    "slug": "the-rock-snowpark",
    "typical_season_start": null,
    "typical_season_end": null,
    "nearest_airport_code": "MKE",
    "nearest_airport_name": "Milwaukee Mitchell International Airport",
    "annual_snowfall_inches": null,
    "terrain_park_count": null,
    "has_terrain_park": true,
    "has_glades": null,
    "has_tubing": true,
    "has_night_skiing": null,
    "has_lodging": false,
    "vertical_drop_ft": 225,
    "total_acres": 75,
    "total_lifts": 5,
    "longest_run_miles": null,
    "source_url": "https://parksandtrips.com/ski-resort/rswi-the-rock-snowpark/",
    "exact_quote": "smaller than average ski area, with only a maximum of 75 acres available to ski ... vertical drop of only 225 feet ... 39% of its trails are rated as 'beginner'. 38% trails are rated as intermediate ... a high-speed rope tow servicing a great terrain park, a double chair, 2 conveyor lifts and a handle tow ... tubing park fit with several pre-made chutes ... operated under that name from 2012 to 2024 ... reverting to its original designation, Crystal Ridge",
    "notes": "The Rock Snowpark (now Crystal Ridge again as of 2024), Franklin WI. Parks&Trips: 225ft vert, 75ac max, 39/38 beginner/int, 5 lifts (high-speed rope+double chair+2 conveyors+handle tow), tubing park, terrain park. Day-use. MKE Milwaukee ~15mi NE closest commercial."
  },
  {
    "slug": "the-summit-at-snoqualmie",
    "typical_season_start": null,
    "typical_season_end": null,
    "nearest_airport_code": "SEA",
    "nearest_airport_name": "Seattle-Tacoma International Airport",
    "annual_snowfall_inches": 435,
    "terrain_park_count": null,
    "has_terrain_park": true,
    "has_glades": true,
    "has_tubing": true,
    "has_night_skiing": true,
    "has_lodging": null,
    "vertical_drop_ft": 2280,
    "total_acres": 1914,
    "total_lifts": 25,
    "longest_run_miles": 1.2,
    "source_url": "https://en.wikipedia.org/wiki/The_Summit_at_Snoqualmie",
    "exact_quote": "2,280 ft (695 m) ... 1,914 acres (7.7 km2) (combined) ... 62 (combined) ... 20 chairs, 5 surface lifts ... Internationale 1.2 mi (1.9 km) ... 435 inches (36.3 ft; 11.0 m) ... Summit Central is also home to a large terrain park ... Summit East is where to go for glade skiing ... The Summit Tubing Center, adjacent to Summit Central, has 20 machine-groomed lanes ... Alpental had night skiing from the beginning",
    "notes": "The Summit at Snoqualmie WA (4 base areas: Alpental, Central, West, East). Wikipedia: 2280ft Alpental vert, 1914ac combined, 62 trails combined, 25 lifts (20 chairs+5 surface), Internationale 1.2mi, 435\" snow, terrain park Central, glades East, tubing center w/20 lanes, night ski. SEA Sea-Tac ~70mi W closest commercial."
  },
  {
    "slug": "thrill-hills",
    "typical_season_start": null,
    "typical_season_end": null,
    "nearest_airport_code": "FAR",
    "nearest_airport_name": "Hector International Airport",
    "annual_snowfall_inches": null,
    "terrain_park_count": null,
    "has_terrain_park": true,
    "has_glades": null,
    "has_tubing": true,
    "has_night_skiing": null,
    "has_lodging": null,
    "vertical_drop_ft": 290,
    "total_acres": 30,
    "total_lifts": 3,
    "longest_run_miles": null,
    "source_url": "https://www.ndtourism.com/articles/downhill-skiing-snowboarding-and-tubing",
    "exact_quote": "Thrill Hills has a vertical drop of 290 feet, with a summit at 1,190 feet and a base at 900 feet ... 10 trails and 3 lifts ... 40% beginner and 60% intermediate ... covers 30 acres and has a terrain park, plus downhill skiing, snowboarding, and tubing fun for all ages",
    "notes": "Thrill Hills, Fort Ransom ND (Sheyenne River Valley). ND Tourism: 290ft vert, 30ac, 10 trails (40/60), 3 lifts, terrain park, tubing, updated lodge w/food+bar. Snowfall not specified. FAR Fargo ~85mi E closest commercial."
  },
  {
    "slug": "thunder-ridge-ski-area",
    "typical_season_start": null,
    "typical_season_end": null,
    "nearest_airport_code": "HPN",
    "nearest_airport_name": "Westchester County Airport",
    "annual_snowfall_inches": null,
    "terrain_park_count": 1,
    "has_terrain_park": true,
    "has_glades": null,
    "has_tubing": null,
    "has_night_skiing": true,
    "has_lodging": null,
    "vertical_drop_ft": 403,
    "total_acres": 90,
    "total_lifts": 7,
    "longest_run_miles": null,
    "source_url": "https://en.wikipedia.org/wiki/Thunder_Ridge_Ski_Area",
    "exact_quote": "403 ft. ... 90 acres (360,000 m2) ... 23 trails ... 3 chairlifts, 4 magic carpets ... snowmaking capabilities which can cover 95% of the mountain ... Yes, 1 ... Yes",
    "notes": "Thunder Ridge Ski Area, Patterson NY. Wikipedia: 403ft vert, 90ac, 23 trails (21 in infobox), 7 lifts (3 chairs+4 carpets), 95% snowmaking, 1 park, night skiing. Snowfall not in WP. HPN White Plains ~35mi S closest commercial."
  },
  {
    "slug": "timber-ridge",
    "typical_season_start": null,
    "typical_season_end": null,
    "nearest_airport_code": "AZO",
    "nearest_airport_name": "Kalamazoo/Battle Creek International Airport",
    "annual_snowfall_inches": 60,
    "terrain_park_count": 2,
    "has_terrain_park": true,
    "has_glades": null,
    "has_tubing": true,
    "has_night_skiing": true,
    "has_lodging": false,
    "vertical_drop_ft": 240,
    "total_acres": 50,
    "total_lifts": 8,
    "longest_run_miles": null,
    "source_url": "https://en.wikipedia.org/wiki/Timber_Ridge_Ski_Area",
    "exact_quote": "The longest vertical drop is 240 feet (73 m) ... There are 50 acres (200,000 m2) of skiable terrain ... Timber Ridge has 15 total trails ... There are eight total ski lifts ... mountain gets about five feet of powder a season ... two terrain parks ... Timber Ridge offers a tubing run ... Adult tickets can be bought on a full-day or night-time basis ... Snowshoe Bar and Cedar Chalet",
    "notes": "Timber Ridge Ski Area, Gobles MI. Wikipedia: 240ft vert, 50ac, 15 trails (input listed difficulty for 47/33/20 split), 8 lifts (2 doubles+1 triple+1 quad+3 ropes+1 surface), ~60\" snow (5ft), 2 parks, tubing run, night skiing. Lodge no overnight. AZO Kalamazoo ~25mi closest commercial."
  },
  {
    "slug": "timberline-lodge",
    "typical_season_start": null,
    "typical_season_end": null,
    "nearest_airport_code": "PDX",
    "nearest_airport_name": "Portland International Airport",
    "annual_snowfall_inches": 540,
    "terrain_park_count": null,
    "has_terrain_park": true,
    "has_glades": null,
    "has_tubing": null,
    "has_night_skiing": true,
    "has_lodging": true,
    "vertical_drop_ft": 4540,
    "total_acres": 1685,
    "total_lifts": 9,
    "longest_run_miles": 3.12,
    "source_url": "https://en.wikipedia.org/wiki/Timberline_Lodge_ski_area",
    "exact_quote": "4,540 ft (1,384 m) ... 1,685 acres (682 ha) ... 35 ... 7 chairlifts, 1 rope tow, 1 magic carpet ... 3.12 mi (5 km) ... yearly snowfall: 45 ft (14 m) ... Yes ... Yes, 3 chairlifts ... 60 miles (100 km) west",
    "notes": "Timberline Lodge Ski Area, Mt. Hood OR. Wikipedia: 4540ft vert, 1685ac, 35 trails, 9 lifts (7 chairs+rope+carpet), 3.12mi longest, 540\" (45ft) snow, terrain park yes, night ski 3 chairs. Iconic Timberline Lodge on-site. PDX Portland ~60mi W."
  },
  {
    "slug": "timberline-mountain",
    "typical_season_start": null,
    "typical_season_end": null,
    "nearest_airport_code": "CKB",
    "nearest_airport_name": "North Central West Virginia Airport",
    "annual_snowfall_inches": 200,
    "terrain_park_count": 2,
    "has_terrain_park": true,
    "has_glades": true,
    "has_tubing": null,
    "has_night_skiing": true,
    "has_lodging": true,
    "vertical_drop_ft": 1000,
    "total_acres": 100,
    "total_lifts": 4,
    "longest_run_miles": 2.0,
    "source_url": "https://en.wikipedia.org/wiki/Timberline_Mountain",
    "exact_quote": "1000 feet (304 m) ... 100 acres (0.4 km2) ... 23 total ... Two surface lifts, one quad chairlift, and one six-pack chairlift ... Salamander ... 2 mi (3.2 km) ... longest slope in the Mid-Atlantic region ... 200 in (510 cm) ... Two parks named Snow Squall and Thunder Snow ... Two glade trails—Pearly Glades and Glade Runner ... Held on select nights on 8 trails ... a hotel",
    "notes": "Timberline Mountain, Davis WV (Canaan Valley). Wikipedia: 1000ft vert, 100ac, 23 trails, 4 lifts (2 surface+quad+six-pack), Salamander 2mi (Mid-Atlantic longest), 200\" snow, 2 parks, 2 glade trails, night ski select 8 trails, hotel lodging. CKB Clarksburg ~75mi closest commercial."
  },
  {
    "slug": "titcomb-mountain",
    "typical_season_start": null,
    "typical_season_end": null,
    "nearest_airport_code": "AUG",
    "nearest_airport_name": "Augusta State Airport",
    "annual_snowfall_inches": 85,
    "terrain_park_count": null,
    "has_terrain_park": null,
    "has_glades": null,
    "has_tubing": null,
    "has_night_skiing": true,
    "has_lodging": null,
    "vertical_drop_ft": 350,
    "total_acres": 45,
    "total_lifts": 3,
    "longest_run_miles": 0.42,
    "source_url": "https://en.wikipedia.org/wiki/Titcomb_Mountain",
    "exact_quote": "350' vertical drop ... 45 acres (18 ha) ... 16 trails ... 3 lifts (two T-Bars and a Pony lift) ... 2,200 feet (670 m) ... 85 inches (220 cm)/year ... night skiing ... a popular local family mountain",
    "notes": "Titcomb Mountain, Farmington ME. Wikipedia: 350ft vert, 45ac, 16 trails, 3 lifts (2 T-bars+Pony lift), 2200ft (~0.42mi) longest, 85\" snow, night skiing. Volunteer-run family hill. AUG Augusta ~45mi E or BGR Bangor ~95mi closest commercial; PWM Portland ~90mi."
  },
  {
    "slug": "titus-mountain",
    "typical_season_start": null,
    "typical_season_end": null,
    "nearest_airport_code": "MSS",
    "nearest_airport_name": "Massena International Airport",
    "annual_snowfall_inches": 150,
    "terrain_park_count": null,
    "has_terrain_park": null,
    "has_glades": true,
    "has_tubing": true,
    "has_night_skiing": null,
    "has_lodging": null,
    "vertical_drop_ft": 1200,
    "total_acres": 380,
    "total_lifts": 12,
    "longest_run_miles": null,
    "source_url": "https://en.wikipedia.org/wiki/Titus_Mountain",
    "exact_quote": "1,200 ft (370 m) ... 380 acres (1,500,000 m2) ... 52 ... 10 chairs: (2 triple, 6 double) ... 2 surface lifts ... 150in (279cm) ... 52 trails and glades over three inter-connected mountains ... operates 10 lifts and a three-lane tubing hill",
    "notes": "Titus Mountain Family Ski Center, Malone NY (north country). Wikipedia: 1200ft vert, 380ac, 52 trails+glades, 12 lifts (10 chairs+2 surface), 150\" snow, glades, 3-lane tubing. MSS Massena ~25mi N or BTV Burlington VT ~85mi (via lake) closest commercial."
  },
  {
    "slug": "trapp-family-lodge",
    "typical_season_start": null,
    "typical_season_end": null,
    "nearest_airport_code": "BTV",
    "nearest_airport_name": "Burlington International Airport",
    "annual_snowfall_inches": null,
    "terrain_park_count": null,
    "has_terrain_park": false,
    "has_glades": null,
    "has_tubing": null,
    "has_night_skiing": null,
    "has_lodging": true,
    "vertical_drop_ft": null,
    "total_acres": 2500,
    "total_lifts": 0,
    "longest_run_miles": null,
    "source_url": "https://en.wikipedia.org/wiki/Trapp_Family_Lodge",
    "exact_quote": "67 kilometres (42 mi) of groomed trails and 100 kilometres (62 mi) of un-groomed trails ... cross-country skiing trails were established during winter 1968-69 by Johannes von Trapp ... mountain biking trails, fitness center, tennis courts, pools",
    "notes": "Trapp Family Lodge, Stowe VT. Wikipedia: cross-country only (no alpine lifts), 67km/42mi groomed + 100km/62mi ungroomed, 2500ac property, founded by Von Trapp family. Full lodge accommodations. No alpine vert/lift. Counted 24 trails in input is xc loop count. BTV Burlington ~35mi NW closest commercial."
  },
  {
    "slug": "treetops-resort",
    "typical_season_start": null,
    "typical_season_end": null,
    "nearest_airport_code": "PLN",
    "nearest_airport_name": "Pellston Regional Airport",
    "annual_snowfall_inches": 87,
    "terrain_park_count": 3,
    "has_terrain_park": true,
    "has_glades": null,
    "has_tubing": true,
    "has_night_skiing": null,
    "has_lodging": true,
    "vertical_drop_ft": 225,
    "total_acres": 80,
    "total_lifts": 4,
    "longest_run_miles": null,
    "source_url": "https://www.onthesnow.com/michigan/treetops-resort/ski-resort",
    "exact_quote": "Vertical Drop: 225 feet ... 28 trails across 80 acres of skiable terrain ... 4 lifts of 2 types ... 87 inches of annual snowfall ... 14% beginner runs, 29% intermediate runs, 50% advanced runs, and 7% expert runs ... 24 downhill ski runs, 3 terrain parks, dog-sledding, and extreme tubing",
    "notes": "Treetops Resort, Gaylord MI. OnTheSnow: 225ft vert, 80ac, 24-28 trails (14/29/50/7), 4 lifts, 87\" snow, 3 parks, extreme tubing. Resort hotel lodging. PLN Pellston ~40mi N closest commercial; TVC Traverse City ~70mi."
  },
  {
    "slug": "trollhaugen",
    "typical_season_start": null,
    "typical_season_end": null,
    "nearest_airport_code": "MSP",
    "nearest_airport_name": "Minneapolis-Saint Paul International Airport",
    "annual_snowfall_inches": 51,
    "terrain_park_count": 4,
    "has_terrain_park": true,
    "has_glades": null,
    "has_tubing": true,
    "has_night_skiing": true,
    "has_lodging": null,
    "vertical_drop_ft": 260,
    "total_acres": 90,
    "total_lifts": 8,
    "longest_run_miles": 0.47,
    "source_url": "https://en.wikipedia.org/wiki/Trollhaugen",
    "exact_quote": "Vertical: 260 Feet ... Skiable terrain: 90 acres ... Number of Runs: 30 ... Total Lifts: 8 ... 4 tow ropes and 4 quad lifts ... Longest run: 2500 ft ... Average Snowfall: 50.7inches ... Terrain Parks: 3-4 ... 10 lanes of snow tubing ... Night Skiing: 100% ... open until 3am on Friday nights",
    "notes": "Trollhaugen, Dresser WI. Wikipedia: 260ft vert, 90ac, 30 runs, 8 lifts (4 ropes+4 quads), 2500ft (~0.47mi) longest, 51\" snow, 3-4 parks, 10-lane tubing, 100% night ski (Fri til 3am). MSP ~50mi SW closest commercial."
  },
  {
    "slug": "turner-mountain",
    "typical_season_start": null,
    "typical_season_end": null,
    "nearest_airport_code": "FCA",
    "nearest_airport_name": "Glacier Park International Airport",
    "annual_snowfall_inches": 200,
    "terrain_park_count": null,
    "has_terrain_park": null,
    "has_glades": null,
    "has_tubing": null,
    "has_night_skiing": null,
    "has_lodging": false,
    "vertical_drop_ft": 2110,
    "total_acres": 1000,
    "total_lifts": 1,
    "longest_run_miles": null,
    "source_url": "https://www.skiturner.com/the-mountain",
    "exact_quote": "vertical drop is 2,110 feet with 22 named runs ... one double-chair lift with more than 50% of runs groomed ... 1,000 acres of terrain ... average snowfall is 200 inches ... Black Diamonds account for 60% of runs, More Difficult trails for 30%, and Beginner slopes for 10% ... mostly run by volunteers and operates Friday thru Sunday and Holidays",
    "notes": "Turner Mountain Ski Area, Libby MT (22mi N of Libby). Resort site/Roaming Montana: 2110ft vert, 1000ac, 22 runs (10/30/60), 1 double chair, 200\" snow, volunteer-run Fri-Sun+holidays. Ski Magazine quote 'best lift-assisted powder skiing in the U.S.' Day-use only. FCA Kalispell ~110mi E closest commercial; GPI is same airport code."
  },
  {
    "slug": "turpin-meadow-ranch",
    "typical_season_start": null,
    "typical_season_end": null,
    "nearest_airport_code": "JAC",
    "nearest_airport_name": "Jackson Hole Airport",
    "annual_snowfall_inches": null,
    "terrain_park_count": null,
    "has_terrain_park": false,
    "has_glades": null,
    "has_tubing": null,
    "has_night_skiing": null,
    "has_lodging": true,
    "vertical_drop_ft": null,
    "total_acres": null,
    "total_lifts": 0,
    "longest_run_miles": 3.13,
    "source_url": "https://turpinmeadowranch.com/adventures/nordic-ski/",
    "exact_quote": "over 20km of trail groomed daily and originally designed by two former Nordic Olympians Hans and Nancy Johnstone ... 7 connected loops ... Lodge and Cabin Loop (0.53 miles) to longer ones such as the Summer Homes loop (3.13 miles) ... flat ski trails in the meadow along the banks of the Buffalo River to heart pumping hills ... Fischer skis for rent, daily cross country ski lessons in both skate and classic and snowshoe tours",
    "notes": "Turpin Meadow Ranch, Moran WY (Buffalo Valley near Jackson Hole). XC-only nordic center: 20+km groomed, 7 loops, longest Summer Homes 3.13mi, designed by Hans/Nancy Johnstone Olympians. Luxury cabin/lodge accommodations. No alpine. JAC Jackson Hole ~45mi SW closest commercial."
  },
  {
    "slug": "tussey-mountain",
    "typical_season_start": "December",
    "typical_season_end": "Mid to late March",
    "nearest_airport_code": "UNV",
    "nearest_airport_name": "University Park Airport",
    "annual_snowfall_inches": null,
    "terrain_park_count": null,
    "has_terrain_park": null,
    "has_glades": null,
    "has_tubing": true,
    "has_night_skiing": true,
    "has_lodging": false,
    "vertical_drop_ft": 500,
    "total_acres": 50,
    "total_lifts": 4,
    "longest_run_miles": 0.75,
    "source_url": "https://www.skipa.com/play/by-name/tussey-mountain",
    "exact_quote": "skiing on 50 acres with 3 ski and snowboard lifts and 1 snowtube lift ... Vertical drop is 500 feet and the longest run is .75 miles ... 14 ski trails in total ... snowmaking system covers 90% of skiable terrain, as does slope lighting ... typically open for skiing, boarding, and tubing in December, running through middle (to late) March",
    "notes": "Tussey Mountain, Boalsburg PA (near Penn State). SkiPA: 500ft vert, 50ac, 14 trails (input says 8), 4 lifts (3 ski+1 snowtube), 0.75mi longest, 90% snowmaking+lighting (=night), tubing, Dec-mid/late Mar season. Day-use only. UNV State College ~10mi closest commercial."
  },
  {
    "slug": "tyrol-basin",
    "typical_season_start": null,
    "typical_season_end": null,
    "nearest_airport_code": "MSN",
    "nearest_airport_name": "Dane County Regional Airport",
    "annual_snowfall_inches": null,
    "terrain_park_count": 5,
    "has_terrain_park": true,
    "has_glades": null,
    "has_tubing": true,
    "has_night_skiing": true,
    "has_lodging": null,
    "vertical_drop_ft": 300,
    "total_acres": 32,
    "total_lifts": 6,
    "longest_run_miles": null,
    "source_url": "https://en.wikipedia.org/wiki/Tyrol_Basin",
    "exact_quote": "300 ft ... 32 acres (130,000 m2) ... 22 runs ... 3 chairs, 1 rope, 1 magic carpet, 1 handle tow ... 5 ... In 2019, Tyrol Basin added snow tubing ... Yes",
    "notes": "Tyrol Basin, Mount Horeb WI (near Madison). Wikipedia: 300ft vert, 32ac, 22 runs, 6 lifts (3 chairs+rope+carpet+handle tow), 5 parks, tubing since 2019, night ski. MSN Madison ~25mi E closest commercial."
  },
  {
    "slug": "tyrol-basin-and-snowboard",
    "typical_season_start": null,
    "typical_season_end": null,
    "nearest_airport_code": "MSN",
    "nearest_airport_name": "Dane County Regional Airport",
    "annual_snowfall_inches": null,
    "terrain_park_count": 5,
    "has_terrain_park": true,
    "has_glades": null,
    "has_tubing": true,
    "has_night_skiing": true,
    "has_lodging": null,
    "vertical_drop_ft": 300,
    "total_acres": 32,
    "total_lifts": 6,
    "longest_run_miles": null,
    "source_url": "https://en.wikipedia.org/wiki/Tyrol_Basin",
    "exact_quote": "300 ft ... 32 acres (130,000 m2) ... 22 runs ... 3 chairs, 1 rope, 1 magic carpet, 1 handle tow ... 5 ... In 2019, Tyrol Basin added snow tubing ... Yes",
    "notes": "Tyrol Basin Ski and Snowboard — duplicate slug of tyrol-basin. Same WI resort, Mount Horeb. Wikipedia: 300ft vert, 32ac, 22 runs (input says 24), 6 lifts, 5 parks, tubing, night ski. MSN Madison ~25mi closest commercial. Likely dedupe target."
  }
]
